status_checker_api/__init__.py
status_checker_api/__main__.py
tests/__init__.py
tests/test_status_checker_api.py
status_checker_api-0.5.dist-info/LICENSE
status_checker_api-0.5.dist-info/METADATA
status_checker_api-0.5.dist-info/WHEEL
status_checker_api-0.5.dist-info/entry_points.txt
status_checker_api-0.5.dist-info/top_level.txt
status_checker_api-0.5.dist-info/RECORD
